mrcrypt/__init__.py
mrcrypt/main.py
mrcrypt/materials_manager.py
mrcrypt/cli/__init__.py
mrcrypt/cli/parser.py
mrcrypt-2.0.0.dist-info/METADATA
mrcrypt-2.0.0.dist-info/RECORD
mrcrypt-2.0.0.dist-info/WHEEL
mrcrypt-2.0.0.dist-info/entry_points.txt
mrcrypt-2.0.0.dist-info/top_level.txt
tests/__init__.py
tests/test_cli.py
tests/test_legacy_compat_cmm.py
tests/test_parser.py
tests/integration/__init__.py
tests/integration/test_i_cli.py
